MANIFEST.in
README.md
requirements.txt
setup.py
watchcat/__init__.py
watchcat/__main__.py
watchcat/cli.py
watchcat/info.py
watchcat/snapshot.py
watchcat/util.py
watchcat.egg-info/PKG-INFO
watchcat.egg-info/SOURCES.txt
watchcat.egg-info/dependency_links.txt
watchcat.egg-info/entry_points.txt
watchcat.egg-info/requires.txt
watchcat.egg-info/top_level.txt
watchcat/config/__init__.py
watchcat/config/config.py
watchcat/config/errors.py
watchcat/diff_detector/__init__.py
watchcat/diff_detector/base.py
watchcat/diff_detector/simple.py
watchcat/filter/__init__.py
watchcat/filter/command.py
watchcat/filter/css_selector.py
watchcat/filter/errors.py
watchcat/filter/filter.py
watchcat/filter/textcontent.py
watchcat/notifier/__init__.py
watchcat/notifier/command.py
watchcat/notifier/errors.py
watchcat/notifier/file.py
watchcat/notifier/notifier.py
watchcat/notifier/slack_bot.py
watchcat/notifier/slack_webhook.py
watchcat/resource/__init__.py
watchcat/resource/command_resource.py
watchcat/resource/errors.py
watchcat/resource/http_resource.py
watchcat/resource/resource.py
watchcat/storage/__init__.py
watchcat/storage/sql_storage.py
watchcat/storage/storage.py