Metadata-Version: 2.1
Name: watchcat
Version: 0.0.7
Summary: watchcat
Home-page: https://github.com/uec-world-dominators/watchcat
Author: shosatojp,tomy-0000
License: UNKNOWN
Platform: UNKNOWN
Classifier: Programming Language :: Python :: 3
Requires-Python: >=3.6
